ksvd/__init__.py
ksvd-0.0.2.dist-info/DESCRIPTION.rst
ksvd-0.0.2.dist-info/METADATA
ksvd-0.0.2.dist-info/RECORD
ksvd-0.0.2.dist-info/WHEEL
ksvd-0.0.2.dist-info/metadata.json
ksvd-0.0.2.dist-info/top_level.txt
